BRIntel/__init__.py
BRIntel/otx/__init__.py
BRIntel/xfe/__init__.py
BRIntel1-0.1.4.dist-info/METADATA
BRIntel1-0.1.4.dist-info/WHEEL
BRIntel1-0.1.4.dist-info/entry_points.txt
BRIntel1-0.1.4.dist-info/top_level.txt
BRIntel1-0.1.4.dist-info/RECORD
