Metadata-Version: 2.1
Name: BRIntel1
Version: 0.1.4
Summary: Ferramenta de coleta de inteligência em websites brasileiros.
Home-page: https://github.com/devfoundsec/BRIntelcollector
Author: ['Matheus Oliveira matheusoliveiratux4me@gmail.com', 'Julio Lira jul10l1r4@disroot.org']
Author-email: ['matheusoliveiratux4me@gmail.com', 'jul10l1r4@disroot.org']
License: MIT License
Classifier: Intended Audience :: System Administrators
Classifier: Programming Language :: Python :: 3
Classifier: Topic :: Security
Classifier: Topic :: Software Development :: Libraries :: Python Modules
Requires-Dist: requests >=2.26.0
Requires-Dist: beautifulsoup4 >=4.10.0
